contrail/__init__.py
contrail/__main__.py
contrail/configuration.py
contrail/contrail.py
contrail/main.py
contrail/crawler/__init__.py
contrail/crawler/crawler.py
contrail/crawler/s3upload.py
contrail/crawler/providers/__init__.py
contrail/crawler/providers/aws_ec2.py
contrail/crawler/providers/aws_ec2_spot.py
contrail/crawler/providers/azure.py
contrail/frontend/__init__.py
contrail/frontend/field_info.py
contrail/frontend/query.py
contrail/frontend/apps/__init__.py
contrail/frontend/apps/api/__init__.py
contrail/frontend/apps/api/apps.py
contrail/frontend/apps/api/urls.py
contrail/frontend/apps/api/views.py
contrail/frontend/apps/contrailsite/__init__.py
contrail/frontend/apps/contrailsite/apps.py
contrail/frontend/apps/contrailsite/forms.py
contrail/frontend/apps/contrailsite/urls.py
contrail/frontend/apps/contrailsite/views.py
contrail/frontend/apps/contrailsite/templatetags/__init__.py
contrail/frontend/apps/contrailsite/templatetags/contrail.py
contrail/frontend/settings/__init__.py
contrail/frontend/settings/settings.py
contrail/frontend/settings/urls.py
contrail/frontend/settings/wsgi.py
contrail/loader/__init__.py
contrail/loader/loader.py
contrail/loader/normalizers.py
contrail/loader/s3iterator.py
contrail/loader/warehouse.py
contrail/loader/loaders/__init__.py
contrail/loader/loaders/aws_ec2.py
contrail/loader/loaders/aws_ec2_spot.py
contrail/loader/loaders/azure.py
contrail/loader/loaders/example_loader.py
test/__init__.py
test/crawler/__init__.py
test/crawler/providers/__init__.py
test/crawler/providers/test_aws_ec2.py
test/crawler/providers/test_aws_ec2_spot.py
test/crawler/providers/test_azure.py
test/crawler/providers/test_base_provider.py
test/loader/__init__.py
test/loader/loaders/__init__.py
test/loader/loaders/aws_ec2/__init__.py
test/loader/loaders/aws_ec2/test_load_aws_ec2.py
test/loader/loaders/aws_ec2_spot/__init__.py
test/loader/loaders/aws_ec2_spot/test_load_aws_ec2_spot.py
test/loader/loaders/azure/__init__.py
contrail-1.0.2.dist-info/LICENSE
contrail-1.0.2.dist-info/METADATA
contrail-1.0.2.dist-info/WHEEL
contrail-1.0.2.dist-info/entry_points.txt
contrail-1.0.2.dist-info/top_level.txt
contrail-1.0.2.dist-info/RECORD
