Metadata-Version: 2.1
Name: contrail
Version: 1.0.2
Summary: Public cloud market price tracker for Amazon EC2 and Azure
Home-page: https://github.com/joshuaprince/Contrail
License: UNKNOWN
Platform: UNKNOWN
Classifier: Programming Language :: Python :: 3
Classifier: License :: OSI Approved :: MIT License
Classifier: Operating System :: OS Independent
Classifier: Framework :: Django :: 2.2
Classifier: Intended Audience :: System Administrators
Requires-Dist: boto3
Requires-Dist: cachetools
Requires-Dist: Django (<3)
Requires-Dist: django-crispy-forms
Requires-Dist: infi.clickhouse-orm
Requires-Dist: requests
